edata/__init__.py
edata/const.py
edata/definitions.py
edata/helpers.py
edata/storage.py
edata/connectors/__init__.py
edata/connectors/datadis.py
edata/connectors/redata.py
edata/processors/__init__.py
edata/processors/base.py
edata/processors/billing.py
edata/processors/consumption.py
edata/processors/maximeter.py
edata/processors/utils.py
e_data-1.2.22.dist-info/LICENSE
e_data-1.2.22.dist-info/METADATA
e_data-1.2.22.dist-info/WHEEL
e_data-1.2.22.dist-info/top_level.txt
e_data-1.2.22.dist-info/RECORD
