Metadata-Version: 2.1
Name: e-data
Version: 1.2.22
Summary: Python library for managing spanish energy data from various web providers
Home-page: https://github.com/uvejota/python-edata
Author: VMG
Author-email: vmayorg@outlook.es
License: GPLv3
Classifier: License :: OSI Approved :: GNU General Public License v3 (GPLv3)
Classifier: Programming Language :: Python
Classifier: Programming Language :: Python :: 3
Classifier: Programming Language :: Python :: 3.6
Classifier: Programming Language :: Python :: 3.7
Classifier: Programming Language :: Python :: 3.8
Classifier: Programming Language :: Python :: 3.9
Classifier: Programming Language :: Python :: Implementation :: CPython
Classifier: Programming Language :: Python :: Implementation :: PyPy
Requires-Python: >=3.6.0
License-File: LICENSE
Requires-Dist: dateparser>=1.1.2
Requires-Dist: freezegun>=1.2.1
Requires-Dist: holidays>=0.14.2
Requires-Dist: pytest>=7.1.2
Requires-Dist: python-dateutil>=2.8.2
Requires-Dist: requests>=2.28.1
Requires-Dist: voluptuous>=0.13.1
Requires-Dist: Jinja2>=3.1.2
